litchi/__init__.py
litchi/app.py
litchi/lang/__init__.py
litchi/lang/base.py
litchi/lang/brython.py
litchi/lang/py2js.py
litchi/lang/server.py
litchi/lang/skulpt.py
litchi/uix/__init__.py
litchi/uix/button.py
litchi/uix/html.py
litchi/uix/label.py
litchi/uix/table.py
litchi_web-0.2.7.2021811.post1.dist-info/LICENSE
litchi_web-0.2.7.2021811.post1.dist-info/METADATA
litchi_web-0.2.7.2021811.post1.dist-info/WHEEL
litchi_web-0.2.7.2021811.post1.dist-info/top_level.txt
litchi_web-0.2.7.2021811.post1.dist-info/RECORD
