Metadata-Version: 2.1
Name: litchi-web
Version: 0.2.7.2021811-1
Summary: Build website with only Python
Home-page: http://github.com/streetartist/Litchi
Author: Streetartist
Author-email: 15252635839@163.com
License: UNKNOWN
Keywords: web,framework,flask
Platform: UNKNOWN
Requires-Python: >=3
Requires-Dist: peewee
Requires-Dist: flask
Requires-Dist: javascripthon
